honeybee/1_🐝_app.py
honeybee/__init__.py
honeybee/__main__.py
honeybee/misconfigurations_catalog.json
honeybee/pages/1_⏳_history.py
honeybee/pages/2_🌐️_network.py
honeybee/prompts/analyze_misconfig.md
honeybee/prompts/extract_application.md
honeybee/prompts/find_misconfig.md
honeybee/prompts/generate_dockercompose.md
honeybee/prompts/generate_dockerfile.md
honeybee/prompts/list_misconfig.md
honeybee/prompts/write_nuclei_rule.md
honeybee/src/client_provider.py
honeybee/src/generators.py
honeybee/src/local_deploy.py
honeybee/src/query_history.py
honeybee/src/settings.py
honeybee/src/trace_tools.py
honeybee/src/validations.py
honeybee/tabs/dockercompose_tab.py
honeybee/tabs/dockerfile_tab.py
honeybee/tabs/nuclei_tab.py
pyhoneybee-0.1.0.dist-info/licenses/LICENSE
pyhoneybee-0.1.0.dist-info/METADATA
pyhoneybee-0.1.0.dist-info/WHEEL
pyhoneybee-0.1.0.dist-info/entry_points.txt
pyhoneybee-0.1.0.dist-info/top_level.txt
pyhoneybee-0.1.0.dist-info/RECORD
