Metadata-Version: 2.4
Name: pyhoneybee
Version: 0.1.0
Summary: HoneyBee: Misconfigured App Generator
Author-email: Yaara Shriki <yaara.shriki@wiz.io>
Project-URL: Homepage, https://github.com/yaaras/honeybee
Project-URL: Issues, https://github.com/yaaras/honeybee/issues
Classifier: Programming Language :: Python :: 3
Classifier: Operating System :: OS Independent
Requires-Python: >=3.9
License-File: LICENSE
Requires-Dist: PyYAML==6.0.2
Requires-Dist: Requests==2.32.3
Requires-Dist: streamlit==1.46.0
Requires-Dist: yamllint==1.37.0
Requires-Dist: openai==1.66.2
Requires-Dist: tqdm==4.67.0
Requires-Dist: yamlfix==1.17.0
Requires-Dist: PyJWT>=2.8.0
Requires-Dist: scapy==2.6.1
Requires-Dist: boto3==1.34.26
Requires-Dist: oyaml==1.0
Dynamic: license-file
